sbomgen/main.py
sbomgen/Parsers/conanParser.py
sbomgen/Parsers/dartParser.py
sbomgen/Parsers/dotnetParser.py
sbomgen/Parsers/gomodParser.py
sbomgen/Parsers/gradleGroovyParser.py
sbomgen/Parsers/gradlekotlinDSLParser.py
sbomgen/Parsers/mavenParser.py
sbomgen/Parsers/npmParser.py
sbomgen/Parsers/phpParser.py
sbomgen/Parsers/requirementsParser.py
sbomgen/Parsers/rubyParser.py
sbomgen/Parsers/rustParser.py
sbomgen/Parsers/swiftParser.py
sbomgen/Parsers/yarnParser.py
sbomgen/Utility/helpers.py
sbomgen-1.0.2.dist-info/License.txt
sbomgen-1.0.2.dist-info/METADATA
sbomgen-1.0.2.dist-info/WHEEL
sbomgen-1.0.2.dist-info/entry_points.txt
sbomgen-1.0.2.dist-info/top_level.txt
sbomgen-1.0.2.dist-info/RECORD
