Metadata-Version: 2.1
Name: sbomgen
Version: 1.0.2
Summary: SBOM Generator in cyclonedx format
Author: cd dev
Author-email: akashsah2003@gmail.com
License-File: License.txt
Requires-Dist: datetime
Requires-Dist: argparse
Requires-Dist: toml
Requires-Dist: pyyaml
Requires-Dist: dicttoxml
